<Defs>
	<ResearchProjectDef Abstract="True" Name="GW_SM_TotETechBase" ParentName="GW_ImperiumTechBase">
		<techLevel>Spacer</techLevel>
	</ResearchProjectDef>
	
	<ResearchProjectDef ParentName="GW_SM_TotETechBase">
		<defName>GW_TotE_CustodesFabrication</defName>
		<label>Custodes fabrication</label>
		<description>Recover schematics for the armor and weapons of the Adeptus Custodes, the bodyguard force of the God-Emperor of Mankind.</description>
        <baseCost>2000</baseCost>
		<prerequisites>
			<li>AdvancedFabrication</li>
			<li MayRequire="happypurging.ageofdarkness">GW_SM_AstartesFabrication</li>
			<!-- <li MayRequire="grimworld.talonoftheemperor">GW_SM_CodexAstartes</li> -->
		</prerequisites>
		<researchViewX>7.00</researchViewX>
		<researchViewY>1.60</researchViewY>
	</ResearchProjectDef>

	<ResearchProjectDef ParentName="GW_SM_TotETechBase">
		<defName>GW_TotE_CustodesGuard</defName>
		<label>Custodian Guard</label>
		<description>Begin production of equipment for the battleline Hykanatoi, also know as the Custodian Guard.</description>
        <baseCost>8500</baseCost>
		<prerequisites>
			<li>GW_TotE_CustodesFabrication</li>
			<!-- <li MayRequire="grimworld.talonoftheemperor">GW_SM_CodexAstartes</li> -->
		</prerequisites>
		<researchViewX>8.00</researchViewX>
		<researchViewY>1.60</researchViewY>
		<modExtensions>
            <li Class="GW_Frame.DefModExtension_ExtraPrerequisiteActions">
                <StudyLocation>GW_Cogitator</StudyLocation>
                <ItemStudyRequirements>
                    <li Class="GW_Frame.StudyRequirement">
                        <StudyObject>GW_STC_Fragment</StudyObject>
                        <NumberRequired>5</NumberRequired>
                    </li>    
                </ItemStudyRequirements>
            </li>
        </modExtensions>
	</ResearchProjectDef>

	<ResearchProjectDef ParentName="GW_SM_TotETechBase">
		<defName>GW_TotE_Allarus</defName>
		<label>Allarus Terminator</label>
		<description>Produce heavy Auramite-plated suits of Terminator Armor, worn by the Allarus Custodians.</description>
        <baseCost>5000</baseCost>
		<prerequisites>
			<li MayRequire="happypurging.ageofdarkness">GW_TotE_CustodesGuard</li>
		</prerequisites>
		<researchViewX>9.00</researchViewX>
		<researchViewY>1.60</researchViewY>
		<modExtensions>
            <li Class="GW_Frame.DefModExtension_ExtraPrerequisiteActions">
                <StudyLocation>GW_Cogitator</StudyLocation>
                <ItemStudyRequirements>
                    <li Class="GW_Frame.StudyRequirement">
                        <StudyObject>GW_STC_Fragment</StudyObject>
                        <NumberRequired>6</NumberRequired>
                    </li>    
                </ItemStudyRequirements>
            </li>
        </modExtensions>
	</ResearchProjectDef>

	<ResearchProjectDef ParentName="GW_SM_TotETechBase">
		<defName>GW_TotE_Castellan</defName>
		<label>Castellan</label>
		<description>Recreate the Castellan Plate, the armor of Captain-General Trajann Valoris, leader of the Adeptus Custodes.</description>
        <baseCost>5000</baseCost>
		<prerequisites>
			<li>GW_TotE_Allarus</li>
		</prerequisites>
		<researchViewX>10.00</researchViewX>
		<researchViewY>1.60</researchViewY>	  
		<modExtensions>
            <li Class="GW_Frame.DefModExtension_ExtraPrerequisiteActions">
                <StudyLocation>GW_Cogitator</StudyLocation>
                <ItemStudyRequirements>
                    <li Class="GW_Frame.StudyRequirement">
                        <StudyObject>GW_STC_Fragment</StudyObject>
                        <NumberRequired>7</NumberRequired>
                    </li>    
                </ItemStudyRequirements>
            </li>
        </modExtensions>
	</ResearchProjectDef>

</Defs>
